{
  "id": "act-9913",
  "type": "statute",
  "title": "Закон за изменение и допълнение на Закона за развитието на академичния състав в Република България",
  "short_name": "053-09-45",
  "status": "in_force",
  "issued_date": "2010-11-25",
  "in_force_date": "2010-12-17",
  "url": "https://www.parliament.bg/bg/laws/ID/9913",
  "description": "Official promulgated act published by the National Assembly of the Republic of Bulgaria (act ID 9913).",
  "provisions": [
    {
      "provision_ref": "97",
      "section": "97",
      "title": "Чл. 97.",
      "content": "Чл. 97. Този раздел не се прилага за конкурсите за заемане на академични длъжности.“\n2. В чл. 328, ал. 1, т. 10 запетаята след думата „доценти“ и думите „старши научни сътрудници I и II степен“ се заличават.\n3. В чл. 330, ал. 2, т. 2 думите „отнето научното звание или“ се заменят с „отнета“, а думите „придобитото звание или“ се заменят с „придобитата“.\n§ 49. В Наказателно-процесуалния кодекс (обн., ДВ, бр. 86 от 2005 г.; изм., бр. 46 и 109 от 2007 г., бр. 69 и 109 от 2008 г., бр. 12, 27, 32 и 33 от 2009 г. и бр. 15 и 32 от 2010 г.) в чл. 145, ал. 1 запетаята след думите „научната степен“ и думите „научното звание“ се заличават.\n§ 50. В Закона за Българската академия на науките (обн., ДВ, бр. 85 от 1991 г.; изм., бр. 90 от 1993 г., бр. 123 от 1997 г. и бр. 41 от 2007 г.) се правят следните изменения:\n1. В чл. 5, ал. 1, изречение второ след думата „учените“ се поставя запетая и думите „с научна степен или звание от“ се заменят със „заемащи длъжности в“.\n2. В чл. 8, ал. 2 запетаята след думата „Професорите“ и думите „старшите научни сътрудници I степен“ се заличават.\n§ 51. В Закона за отбраната и въоръжените сили на Република България (обн., ДВ, бр. 35 от 2009 г.; изм., бр. 74, 82, 93 и 99 от 2009 г., бр. 16, 88 и 98 от 2010 г.) се правят следните изменения:\n1. В чл. 94, ал. 1 думите „Закона за научните степени и научните звания“ се заменят със „Закона за развитието на академичния състав в Република България“.\n2. В чл. 97:\nа) в ал. 4 запетаята след думата „преподавателски“ се заличава, а думите „научно-преподавателски и изследователски“ се заменят с „и академични“;\nб) в ал. 5 думата „научно-преподавателски“ се заменя с „академични“.\n3. В чл. 160, ал. 3 след думата „лицата“ се поставя запетая, а думите „с научно звание „доцент“ или „старши научен сътрудник II степен“ и „професор“ или „старши научен сътрудник I степен“ се заменят със „заемащи академичните длъжности „доцент“ или „професор“.\n4. В чл. 291 думите „научно-преподавателски и научноизследователски“ се заменят с „и академични“, а думите „Закона за научните степени и научните звания“ се заменят със „Закона за развитието на академичния състав в Република България“.\n§ 52. В Закона за задължителното депозиране на печатни и други произведения (обн., ДВ, бр. 108 от 2000 г.; изм., бр. 28, 88 и 94 от 2005 г., бр. 57 от 2007 г., бр. 42 и 82 от 2009 г. и бр. 87 от 2010 г.) се правят следните изменения:\n1. В чл. 5, ал. 1, т. 2 думите „научни звания след“ се заменят с „назначават на академични длъжности след“.\n2. В чл. 8, ал. 6 думите „научното звание“ се заменят с „от заемане на академичната длъжност“.\n§ 53. В Закона за културното наследство (обн., ДВ, бр. 19 от 2009 г.; Решение № 7 на Конституционния съд от 2009 г. – бр. 80 от 2009 г.; изм., бр. 92 и 93 от 2009 г.) се правят следните изменения:\n1. В чл. 28, ал. 4, изречение първо думите „научно звание“ се заменят със „заемащи академична длъжност“.\n2. В чл. 99, ал. 3 думите „и звания“ се заменят с „или заемащи академични длъжности“.\n§ 54. В Закона за адвокатурата (обн., ДВ, бр. 55 от 2004 г.; изм. и доп., бр. 43 и 79 от 2005 г., бр. 10, 39 и 105 от 2006 г., бр. 59 от 2007 г., бр. 69 от 2008 г. и бр. 53 от 2010 г.) в чл. 5 се правят следните изменения:\n1. В ал. 2, т. 3 думите „е преподавател по правни науки във висше училище или научен сътрудник по правни науки в научен институт“ се заменят със „заема академична длъжност по правни науки във висше училище или научна организация“.\n2. В ал. 4 запетаята след думата „представители“ се заличава, думите „преподавателите по правни науки във висшите училища и научните сътрудници по правни науки в научните институти“ се заменят с „и лицата, заемащи академични длъжности по правни науки във висшите училища или в научните организации“ и след тях се поставя запетая.\n§ 55. В Закона за съсловната организация на магистър-фармацевтите (обн., ДВ, бр. 75 от 2006 г.; изм., бр. 105 от 2006 г., бр. 31 от 2007 г., бр. 13 и 71 от 2008 г., бр. 41 от 2009 г. и бр. 98 от 2010 г.) се правят следните изменения:\n1. В чл. 31, ал. 3, т. 2 думите „и звание“ се заличават.\n2. В чл. 33, ал. 1, т. 4 запетаята след думите „научната степен“ и думите „научното звание“ се заличават.\n§ 56. В Закона за съсловната организация на медицинските сестри, акушерките и асоциираните медицински специалисти (обн., ДВ, бр. 46 от 2005 г.; изм., бр. 85 от 2005 г., бр. 30, 59 и 75 от 2006 г., бр. 41 от 2007 г., бр. 13 от 2008 г., бр. 41 от 2009 г. и бр. 98 от 2010 г.) се правят следните изменения:\n1. В чл. 35, ал. 3 думите „и звание“ се заличават.\n2. В чл. 37, ал. 1, т. 5 запетаята след думите „научната степен“ и думите „научното звание“ и „съответно протокола“ се заличават.\n§ 57. В Закона за съсловните организации на лекарите и на лекарите по дентална медицина (обн., ДВ, бр. 83 от 1998 г.; изм., бр. 70 от 2004 г., бр. 76 и 85 от 2005 г., бр. 30, 59, 75 и 105 от 2006 г., бр. 31 от 2007 г., бр. 13 и 102 от 2008 г., бр. 101 от 2009 г. и бр. 98 от 2010 г.) се правят следните изменения:\n1. В чл. 32, ал. 3, т. 3 думите „и звание“ се заличават.\n2. В чл. 34, ал. 1, т. 5 запетаята след думите „научната степен“ и думите „научното звание“ и „съответно протокола“ се заличават.\n§ 58. В Закона за радиото и телевизията (обн., ДВ, бр. 138 от 1998 г.; Решение № 10 на Конституционния съд от 1999 г. – бр. 60 от 1999 г.; изм. и доп., бр. 81 от 1999 г., бр. 79 от 2000 г., бр. 96 и 112 от 2001 г., бр. 77 и 120 от 2002 г., бр. 99 и 114 от 2003 г., бр. 99 и 115 от 2004 г., бр. 88, 93 и 105 от 2005 г., бр. 21, 34, 70, 80, 105 и 108 от 2006 г., бр. 10, 41, 53 и 113 от 2007 г., бр. 110 от 2008 г., бр. 14, 37, 42 и 99 от 2009 г. и бр. 12, 47 и 97 от 2010 г.) в чл. 57, ал. 3 думите „са в трудово правоотношение с висши училища или научни организации като хабилитирани преподаватели или приравнени на тях научни сътрудници“ се заменят със „заемат академични длъжности във висши училища или научни организации“.\n§ 59. (1) В срок до един месец от влизането в сила на този закон Министерският съвет изменя и допълва правилника по § 9, ал. 2 от преходните и заключителните разпоредби.\n(2) В едномесечен срок от влизането в сила на изменението и допълнението на правилника по ал. 1 висшите училища и научните организации привеждат своите правилници в съответствие с изискванията на този закон и правилника за неговото прилагане.\nЗаконът е приет от 41-ото Народно събрание на 17 декември 2010 г. и е подпечатан с официалния печат на Народното събрание.\nПредседател на Народното събрание:\nЦецка Цачева\n10792"
    }
  ],
  "definitions": []
}