{
  "id": "act-10084",
  "type": "statute",
  "title": "Закон за ратифициране на Меморандума за разбирателство между Министерството на икономиката, енергетиката и туризма на Република България и Министерството на бизнеса и търговията на Държавата Катар",
  "short_name": "002-02-53",
  "status": "in_force",
  "issued_date": "2010-12-10",
  "in_force_date": "2011-02-23",
  "url": "https://www.parliament.bg/bg/laws/ID/10084",
  "description": "Official promulgated act published by the National Assembly of the Republic of Bulgaria (act ID 10084).",
  "provisions": [
    {
      "provision_ref": "body",
      "section": "body",
      "title": "Основен текст",
      "content": "УКАЗ № 43\nНа основание чл. 98, т. 4 от Конституцията на Република България\nПОСТАНОВЯВАМ:\nДа се обнародва в „Държавен вестник“ Законът за ратифициране на Меморандума за разбирателство между Министерството на икономиката, енергетиката и туризма на Република България и Министерството на бизнеса и търговията на Държавата Катар, приет от ХLI Народно събрание на 23 февруари 2011 г.\nИздаден в София на 2 март 2011 г.\nПрезидент на републиката: Георги Първанов\nПодпечатан с държавния печат.\nМинистър на правосъдието: Маргарита Попова\nЗАКОН\nза ратифициране на Меморандума за разбирателство между Министерството на икономиката, енергетиката и туризма на Република България и Министерството на бизнеса и търговията на Държавата Катар\nЧлен единствен. Ратифицира Меморандума за разбирателство между Министерството на икономиката, енергетиката и туризма на Република България и Министерството на бизнеса и търговията на Държавата Катар, подписан на 23 март 2010 г. в Доха, Катар, с направеното в него изменение чрез размяна на ноти от 16 юни 2010 г. и 24 септември 2010 г.\nЗаконът е приет от 41-ото Народно събрание на 23 февруари 2011 г. и е подпечатан с официалния печат на Народното събрание.\nПредседател на Народното събрание: Цецка Цачева\n2663"
    }
  ],
  "definitions": []
}