{
  "id": "act-13917",
  "type": "statute",
  "title": "Закон за денонсиране на Споразумението за Международната организация за спътникови телекомуникации ИНТЕЛСАТ",
  "short_name": "202-01-18",
  "status": "in_force",
  "issued_date": "2012-03-30",
  "in_force_date": "2012-04-11",
  "url": "https://www.parliament.bg/bg/laws/ID/13917",
  "description": "Official promulgated act published by the National Assembly of the Republic of Bulgaria (act ID 13917).",
  "provisions": [
    {
      "provision_ref": "body",
      "section": "body",
      "title": "Основен текст",
      "content": "УКАЗ № 162\nНа основание чл.&ensp;98, т.&ensp;4 от Конституцията на Република България\nПОСТАНОВЯВАМ:\nДа се обнародва в „Държавен вестник“ Законът за денонсиране на Споразумението за Международната организация за спътникови телекомуникации ИНТЕЛСАТ, приет от ХLI Народно събрание на 11 април 2012 г.\nИздаден в София на 19 април 2012&ensp;г.\nПрезидент на републиката: Росен Плевнелиев\nПодпечатан с държавния печат.\nМинистър на правосъдието: Диана Ковачева\nЗАКОН\nза денонсиране на Споразумението за Международната организация за спътникови телекомуникации ИНТЕЛСАТ\nЧлен единствен. Денонсира Споразумението за Международната организация за спътникови телекомуникации ИНТЕЛСАТ от 20 август 1971 г. с измененията от 2000 г.\nЗаключителна разпоредба\nПараграф единствен. Законът влиза в сила от деня на обнародването му в „Държавен вестник“.\nЗаконът е приет от 41-ото Народно събрание на 11 април 2012 г. и е подпечатан с официалния печат на Народното събрание.\nЗа председател на Народното събрание: Анастас Анастасов\n4051"
    }
  ],
  "definitions": []
}