{
  "id": "act-14954",
  "type": "statute",
  "title": "Закон за ратифициране на Споразумението за асоцииране между Европейския съюз и Европейската общност за атомна енергия и техните държави членки, от една страна, и Грузия, от друга страна",
  "short_name": "402-02-16",
  "status": "in_force",
  "issued_date": "2014-07-10",
  "in_force_date": "2014-07-24",
  "url": "https://www.parliament.bg/bg/laws/ID/14954",
  "description": "Official promulgated act published by the National Assembly of the Republic of Bulgaria (act ID 14954).",
  "provisions": [
    {
      "provision_ref": "body",
      "section": "body",
      "title": "Основен текст",
      "content": "УКАЗ № 192\nНа основание чл. 98, т. 4 от Конституцията на Република България\nПОСТАНОВЯВАМ:\nДа се обнародва в „Държавен вестник“ Законът за ратифициране на Споразумението за асоцииране между Европейския съюз и Европейската общност за атомна енергия и техните държави членки, от една страна, и Грузия, от друга страна, приет от ХLIІ Народно събрание на 24 юли 2014 г.\nИздаден в София на 28 юли 2014 г.\nПрезидент на републиката: Росен Плевнелиев\nПодпечатан с държавния печат.\nМинистър на правосъдието: Зинаида Златанова\nЗАКОН\nза ратифициране на Споразумението за асоцииране между Европейския съюз и Европейската общност за атомна енергия и техните държави членки, от една страна, и Грузия, от друга страна\nЧлен единствен. Ратифицира Споразумението за асоцииране между Европейския съюз и Европейската общност за атомна енергия и техните държави членки, от една страна, и Грузия, от друга страна, подписано на 27 юни 2014 г. в Брюксел.\nЗаконът е приет от 42-то Народно събрание на 24 юли 2014 г. и е подпечатан с официалния печат на Народното събрание.\nПредседател на Народното събрание: Михаил Миков\n5132"
    }
  ],
  "definitions": []
}