{
  "id": "act-15035",
  "type": "statute",
  "title": "Закон за ратифициране на Споразумението за изменение и допълнение на Рамковото споразумение между правителството на Република България и Европейския инвестиционен фонд относно изпълнението на Инициативата JEREMIE в Република България и на Споразумението за изменение и допълнение на Финансовото споразумение между правителството на Република България и Европейския инвестиционен фонд относно изпълнението на Инициативата JEREMIE в Република България",
  "short_name": "402-02-1",
  "status": "in_force",
  "issued_date": "2014-10-31",
  "in_force_date": "2015-01-15",
  "url": "https://www.parliament.bg/bg/laws/ID/15035",
  "description": "Official promulgated act published by the National Assembly of the Republic of Bulgaria (act ID 15035).",
  "provisions": [
    {
      "provision_ref": "body",
      "section": "body",
      "title": "Основен текст",
      "content": "УКАЗ № 6\nНа основание чл. 98, т. 4 от Конституцията на Република България\nПОСТАНОВЯВАМ:\nДа се обнародва в „Държавен вестник“ Законът за ратифициране на Споразумението за изменение и допълнение на Рамковото споразумение между правителството на Република България и Европейския инвестиционен фонд относно изпълнението на Инициативата JEREMIE в Република България и на Споразумението за изменение и допълнение на Финансовото споразумение между правителството на Република България и Европейския инвестиционен фонд относно изпълнението на Инициативата JEREMIE в Република България, приет от ХLIIІ Народно събрание на 15 януари 2015 г.\nИздаден в София на 20 януари 2015 г.\nПрезидент на републиката: Росен Плевнелиев\nПодпечатан с държавния печат.\nМинистър на правосъдието: Христо Иванов\nЗАКОН\nза ратифициране на Споразумението за изменение и допълнение на Рамковото споразумение между правителството на Република България и Европейския инвестиционен фонд относно изпълнението на Инициативата JEREMIE в Република България и на Споразумението за изменение и допълнение на Финансовото споразумение между правителството на Република България и Европейския инвестиционен фонд относно изпълнението на Инициативата JEREMIE в Република България\nЧлен единствен. Ратифицира Споразумението за изменение и допълнение на Рамковото споразумение между правителството на Република България и Европейския инвестиционен фонд относно изпълнението на Инициативата JEREMIE в Република България и Споразумението за изменение и допълнение на Финансовото споразумение между правителството на Република България и Европейския инвестиционен фонд относно изпълнението на Инициативата JEREMIE в Република България, подписани на 24 октомври 2014 г.\nЗаключителна разпоредба\nПараграф единствен. Законът влиза в сила от деня на обнародването му в „Държавен вестник“.\nЗаконът е приет от 43-то Народно събрание на 15 януари 2015 г. и е подпечатан с официалния печат на Народното събрание.\nПредседател на Народното събрание: Цецка Цачева\n294"
    }
  ],
  "definitions": []
}