{
  "id": "act-15210",
  "type": "statute",
  "title": "Закон за ратифициране на Споразумението между правителството на Република България и правителството на Съединените американски щати за подобряване спазването на данъчното законодателство в международен аспект и въвеждането в действие на FATCA",
  "short_name": "502-02-2",
  "status": "in_force",
  "issued_date": "2015-02-06",
  "in_force_date": "2015-06-11",
  "url": "https://www.parliament.bg/bg/laws/ID/15210",
  "description": "Official promulgated act published by the National Assembly of the Republic of Bulgaria (act ID 15210).",
  "provisions": [
    {
      "provision_ref": "body",
      "section": "body",
      "title": "Основен текст",
      "content": "УКАЗ № 109\nНа основание чл. 98, т. 4 от Конституцията на Република България\nПОСТАНОВЯВАМ:\nДа се обнародва в „Държавен вестник“ Законът за ратифициране на Споразумението между правителството на Република България и правителството на Съединените американски щати за подобряване спазването на данъчното законодателство в международен аспект и въвеждането в действие на FATCA, приет от ХLІІI Народно събрание на 11 юни 2015 г.\nИздаден в София на 24 юни 2015 г.\nПрезидент на републиката: Росен Плевнелиев\nПодпечатан с държавния печат.\nМинистър на правосъдието: Христо Иванов\nЗАКОН\nза ратифициране на Споразумението между правителството на Република България и правителството на Съединените американски щати за подобряване спазването на данъчното законодателство в международен аспект и въвеждането в действие на FATCA\nЧлен единствен. Ратифицира Споразумението между правителството на Република България и правителството на Съединените американски щати за подобряване спазването на данъчното законодателство в международен аспект и въвеждането в действие на FATCA, подписано на 5 декември 2014 г. в София.\nЗаконът е приет от 43-то Народно събрание на 11 юни 2015 г. и е подпечатан с официалния печат на Народното събрание.\nПредседател на Народното събрание: Цецка Цачева\n4051"
    }
  ],
  "definitions": []
}