{
  "id": "act-15664",
  "type": "statute",
  "title": "Закон за изменение и допълнение на Закона за подпомагане и финансова компенсация на пострадали от престъпления",
  "short_name": "502-01-98",
  "status": "in_force",
  "issued_date": "2015-12-14",
  "in_force_date": "2016-06-22",
  "url": "https://www.parliament.bg/bg/laws/ID/15664",
  "description": "Official promulgated act published by the National Assembly of the Republic of Bulgaria (act ID 15664).",
  "provisions": [
    {
      "provision_ref": "6б",
      "section": "6б",
      "title": "Чл. 6б.",
      "content": "Чл. 6б. Задграничните представителства на Република България в държавите – членки на Европейския съюз, информират писмено българските граждани, които се намират там и са пострадали от престъпления на територията на приемащата държава, както и лицата по чл. 3, ал. 2 – при тяхно желание, за компетентните органи в тази държава, към които могат да се обърнат относно реда за получаване на подпомагане и финансова компенсация, за възможността по чл. 19, ал. 1, както и за условията и реда за получаване на съответния вид подпомагане по чл. 8 – 11 на територията на Република България.“\n§ 4. В чл. 7 се правят следните изменения и допълнения:\n1. В ал. 1, т. 2 думите „както и на лечебни заведения, службите за социално подпомагане“ се заменят с „както и на центровете за спешна медицинска помощ, лечебните заведения за болнична помощ, дирекциите за социално подпомагане“.\n2. В ал. 2 след думите „Министерството на вътрешните работи“ се добавя „Министерството на външните работи“ и се поставя запетая.\n§ 5. В чл. 8 се правят следните изменения и допълнения:\n1. В ал. 1, т. 3 накрая се добавя „по реда на Закона за правната помощ“.\n2. Алинея 3 се изменя така:\n„(3) Формите на подпомагане по ал. 1, т. 2 и 4 се предоставят при спазване на принципа на поверителност преди образуване на наказателно производство, по време на или в подходящ срок след приключване на наказателното производство съобразно нуждите на пострадалите и на лицата по чл. 3, ал. 2.“\n3. Създава се ал. 4:\n„(4) При необходимост безплатната психологическа консултация и помощ по ал. 1, т. 2 се предоставят и след постановяване на решението по чл. 24.“\n§ 6. В чл. 9 се правят следните изменения и допълнения:\n1. В ал. 1 накрая се добавя „съобразно нуждите на пострадалия и психологическото му състояние“.\n2. Алинея 2 се изменя така:\n„(2) Дейността по ал. 1 се финансира от Министерството на правосъдието, като процедурата по избор на организации за подкрепа на пострадали, условията и редът за финансирането, отчитането и контролът върху дейността им се определят с правилника за прилагане на закона при спазване на правилата за държавните помощи.“\n3. Алинея 3 се отменя.\n§ 7. Член 10 се отменя.\n§ 8. В чл. 11 се правят следните допълнения:\n1. В ал. 2 накрая се поставя запетая и се добавя „в предоставянето на информация относно риска от вторично и повторно виктимизиране, от сплашване или отмъщение, както и в предоставяне на съвети относно предотвратяването им“.\n2. Създава се ал. 3:\n„(3) Организациите за подкрепа на пострадали осигуряват подслон или друго подходящо временно настаняване на пострадалите от престъпления, за които е налице непосредствен риск от вторично и повторно виктимизиране, сплашване и отмъщение.“\n§ 9. В чл. 12 се правят следните изменения и допълнения:\n1. Създава се ал. 1:\n„(1) Пострадалите от престъпления имат право на еднократна финансова компенсация при условията и по реда на този закон.“\n2. Досегашният текст става ал. 2 и в нея:\nа) създава се нова т. 2:\n„2. споразумението за решаване на делото в досъдебното производство;“\nб) досегашните т. 2 и 3 стават съответно т. 3 и 4.\n§ 10. Член 13 се изменя така:\n„Чл. 13. (1) Финансовата компенсация се изразява в предоставяне от държавата на парична сума, като максималният й размер за лице по чл. 3, ал. 1 или за лицата по чл. 3, ал. 2 не може да надвишава 10 000 лв.\n(2) Когато финансовата компенсация се предоставя за издръжка на лица по чл. 3, ал. 2, ненавършили 18-годишна възраст, размерът за всяко едно лице е до 10 000 лв.“\n§ 11. В чл. 14 се правят следните изменения и допълнения:\n1. Досегашният текст става ал. 1.\n2. Създава се ал. 2:\n„(2) Редът за установяването на вредите по ал. 1 и изплащането на финансовата компенсация се определят с правилника за прилагане на закона.“\n§ 12. В чл. 18 се правят следните изменения и допълнения:\n1. Алинея 3 се изменя така:\n„(3) Молбата за финансова компенсация се подава до Националния съвет в едногодишен срок от влизането в сила на акта по чл. 12, ал. 2. Молбата може да се подаде и чрез организация за подкрепа на пострадали или чрез областния управител по настоящ адрес на пострадалия.“\n2. В ал. 4 думите „подадена до“ се заменят с „подадена чрез“.\n3. Създава се нова ал. 5:\n„(5) Когато молбата е подадена чрез организация за подкрепа на пострадали, тя се изпраща на Националния съвет в 7-дневен срок от получаването й.“\n4. Досегашните ал. 5 и 6 стават съответно ал. 6 и 7 и се изменят така:\n„(6) Когато молбата за финансова компенсация не е подадена в срока по ал. 3, пострадалият или лицата по чл. 3, ал. 2 представят писмена декларация за причините и обстоятелствата за неспазването на срока. Националният съвет допуска или отказва разглеждане на молбата, за което се мотивира.\n(7) Към молбата се прилагат заверени копия на документите, които удостоверяват посочените в нея данни, включително декларация по образец от пострадалия или от лицата по чл. 3, ал. 2, за обстоятелството по чл. 15, ал. 1, т. 4.“\n5. Създава се ал. 8:\n„(8) Когато пострадалият е гражданин на друга държава – членка на Европейския съюз, за установяване на основанието по чл. 15, ал. 1, т. 1 Националният съвет може да поиска съдействие от компетентните органи на държавата членка, чийто гражданин е пострадалият.“\n6. Досегашната ал. 7 става ал. 9 и се изменя така:\n„(9) Националният съвет предоставя на пострадалия, на областния управител и на организацията за подкрепа на пострадали, когато молбата е постъпила чрез тях, информация за лице за контакт в Министерството на правосъдието, документ за получаването на молбата и срока за произнасяне по нея.“\n§ 13. В чл. 20 се правят следните изменения и допълнения:\n1. В ал. 2 след думите „състои от“ се добавя „постоянни членове“.\n2. Създава се нова ал. 3:\n„(3) По реда на ал. 2 се определят и резервни членове, които заместват постоянните членове при тяхно отсъствие.“\n3. Досегашните ал. 3 и 4 стават съответно ал. 4 и 5.\n§ 14. В чл. 21, т. 2 след думите „разглеждането й“ се поставя запетая и се добавя „образци на формуляра и на протокола по чл. 6а, ал. 2 и 3, на декларацията по чл. 18, ал. 7“.\n§ 15. В чл. 22 ал. 2 се изменя така:\n„(2) Правомощията и дейността на експертната комисия се уреждат с правилника за прилагане на закона.“\n§ 16. В чл. 23 ал. 1 се изменя така:\n„(1) Националният съвет заседава веднъж месечно.“\n§ 17. В чл. 24 се правят следните изменения:\n1. Алинея 1 се изменя така:\n„(1) Молбите за предоставяне на финансова компенсация се разглеждат в едномесечен срок от датата на постъпването им. При необходимост този срок може да бъде удължаван до три месеца.“\n2. Алинея 6 се изменя така:\n„(6) Препис от решението се изпраща незабавно на пострадалия и на областния управител или на организацията за подкрепа на пострадали, когато молбата за финансова компенсация е постъпила чрез тях.“\n3. В ал. 7 думите „чл. 12, т. 3“ се заменят с „чл. 12, ал. 2, т. 4“.\n§ 18. В чл. 25, ал. 2 думите „в специална извънбюджетна сметка“ се заменят с „по бюджета“.\n§ 19. В чл. 28, ал. 1 след думите „чл. 11, ал. 1“ се добавя „и 3 и чл. 18, ал. 5“.\n§ 20. В допълнителната разпоредба се правят следните изменения и допълнения:\n1. Наименованието се изменя така: „Допълнителни разпоредби“.\n2. Създава се § 1а:\n„§ 1а. Този закон въвежда изискванията на Директива 2012/29/ЕС на Европейския парламент и на Съвета от 25 октомври 2012 г. за установяване на минимални стандарти за правата, подкрепата и защитата на жертвите на престъпления и за замяна на Рамково решение 2001/220/ПВР на Съвета (ОВ, L 315/57 от 14 ноември 2012 г.).“\nПреходни и заключителни разпоредби\n§ 21. В тримесечен срок от обнародването на този закон в „Държавен вестник“ Министерският съвет приема правилникa за прилагането на закона.\n§ 22. Подадените до влизането в сила на този закон молби за финансова компенсация се разглеждат при досегашните условия и ред.\n§ 23. В двумесечен срок от обнародването на този закон в „Държавен вестник“ Националният съвет изготвя и предоставя на министъра на правосъдието за утвърждаване образци на формуляра и на протокола по чл. 6а, ал. 2 и 3 и на декларацията по чл. 18, ал. 7.\n§ 24. Законът влиза в сила три месеца след обнародването му в „Държавен вестник“, с изключение на § 21 и 23, които влизат в сила от деня на обнародването.\nЗаконът е приет от 43-то Народно събрание на 22 юни 2016 г. и е подпечатан с официалния печат на Народното събрание.\nПредседател на Народното събрание: Цецка Цачева\n5115"
    }
  ],
  "definitions": []
}