{
  "id": "act-77804",
  "type": "statute",
  "title": "Закон за изменение и допълнение на Закона за публичните финанси",
  "short_name": "702-01-20",
  "status": "in_force",
  "issued_date": "2017-09-29",
  "in_force_date": "2017-11-01",
  "url": "https://www.parliament.bg/bg/laws/ID/77804",
  "description": "Official promulgated act published by the National Assembly of the Republic of Bulgaria (act ID 77804).",
  "provisions": [
    {
      "provision_ref": "152б",
      "section": "152б",
      "title": "Чл. 152б.",
      "content": "Чл. 152б. (1) При банки, обявени в несъстоятелност с влязло в сила решение на съда, наличните към датата на обявяване в несъстоятелност на съответната банка средства по сметки и депозити на бюджетните организации, подлежащи на обезпечаване съгласно чл. 152, ал. 1, се трансформират във вземане на Министерството на финансите към банката и се възстановяват на бюджетните организации в левове за сметка на средства на централния бюджет в Българската народна банка по реда на ал. 2 – 7 и в срока по ал. 17.\n(2) Средствата по ал. 1 се възстановяват за сметка на централния бюджет чрез бюджетите на съответните първостепенни разпоредители с бюджет, като:\n1. за съставните бюджети по държавния бюджет, за които се прилага чл. 15, се залага лимит в системата за електронни бюджетни разплащания за възстановяване на средствата по сметки за чужди средства и сметки за средства от Европейския съюз за сметка на бюджетното взаимоотношение с централния бюджет;\n2. възстановяването на средствата по ал. 1 на съдебната система, социалноосигурителните фондове, общините и техните подведомствени разпоредители с бюджет се извършва чрез превеждане на сумите от централния бюджет по бюджетите на съответните първостепенни разпоредители с бюджет;\n3. възстановяването на средствата по ал. 1 на държавните висши училища и на Българската академия на науките се извършва чрез превеждане на средствата от бюджета на съответния първостепенен разпоредител с бюджет за сметка на бюджетното му взаимоотношение с централния бюджет и залагане на допълнителен лимит в системата за електронни бюджетни разплащания;\n4. възстановяването на средствата по ал. 1 на разпоредителите с бюджет по чл. 13, ал. 3 без тези по т. 3 се извършва от централния бюджет чрез превеждането на сумите по бюджетите на съответните първостепенни разпоредители с бюджет;\n5. за разпоредителите с бюджет по чл. 13, ал. 4 средствата по ал. 1 се възстановяват по бюджетите им чрез превеждане на сумите от бюджета на съответния първостепенен разпоредител с бюджет за сметка на бюджетното му взаимоотношение с централния бюджет и залагане на допълнителен лимит в системата за електронни бюджетни разплащания.\n(3) В случай че средства по ал. 1 на бюджетна организация са съхранявани по обособени банкови сметки за средствата от Европейския съюз, възстановените по реда на ал. 2 такива средства по бюджета на бюджетната организация се прехвърлят по съответните сметки за средствата от Европейския съюз в обслужващите банки.\n(4) В случай че средства по ал. 1 на бюджетна организация са съхранявани по обособени банкови сметки за чужди средства, подлежащите на възстановяване по реда на ал. 2 такива средства по бюджета на бюджетната организация се прехвърлят по съответните сметки за чужди средства в обслужващите банки, освен ако бюджетната организация реши да изплаща задълженията по тези чужди средства директно от бюджета си, без да прехвърля сумите по банкова сметка за чужди средства.\n(5) Операциите по ал. 1, ал. 2, т. 2 – 5, ал. 3 и 4 се отчитат в частта на финансирането на бюджетното салдо.\n(6) При необходимост от плащания от бюджетите на разпоредителите с бюджет по държавния бюджет, социалноосигурителните фондове и бюджетите по ал. 2, т. 3 – 5 за сметка на техни бюджетни средства по ал. 1 лимитът в системата за електронни бюджетни разплащания се определя, актуализира и коригира по общия ред на чл. 132, ал. 2 – 4.\n(7) При прилагането на ал. 2 – 4 подлежащите на възстановяване суми могат да се прихващат с предоставени от централния бюджет на съответните бюджетни организации временни безлихвени заеми, както и с произтичащите от прилагането на чл. 159, ал. 12 – 14, чл. 160 и 161 задължения към държавния бюджет на разпоредители с бюджет, които не са част от държавния бюджет.\n(8) Банката по ал. 1 предоставя на бюджетните организации информация за салдата по техните текущи и депозитни сметки към датата на обявяване в несъстоятелност. Тази информация може да се предостави от банката директно на съответния първостепенен разпоредител с бюджет, при условие че той предостави списък на своите подведомствени разпоредители с бюджет, съдържащ наименованието и ЕИК/БУЛСТАТ на съответните бюджетни организации.\n(9) За целите на прилагане на ал. 1 и 8 съответната бюджетна организация или нейният първостепенен разпоредител с бюджет уточнява с банката коректния размер на средствата по ал. 1 на бюджетната организация в случай на неточности, непълнота или други грешки в информацията по ал. 8.\n(10) Обезпеченията по чл. 152, ал. 9 служат за удовлетворяване на вземането на Министерството на финансите по ал. 1, като се прилага следната поредност:\n1. блокираните вземания на банката по чл. 152, ал. 5;\n2. блокираните вземания на банката по чл. 152, ал. 6;\n3. държавните ценни книжа, блокирани по реда на чл. 152, ал. 3;\n4. държавните ценни книжа, блокирани по реда на чл. 152, ал. 4;\n5. дългът по § 20а от преходните и заключителните разпоредби;\n6. обезпеченията по чл. 152, ал. 8 с ценни книжа, емитирани от Българската народна банка;\n7. обезпеченията по чл. 152, ал. 8 под формата на залог на бързо ликвидни активи, които могат да се използват като обезпечение при отпускане на кредити на банка от Българската народна банка по реда на Закона за Българската народна банка;\n8. обезпеченията по чл. 152, ал. 8 под формата на финансово обезпечение по смисъла на Закона за договорите за финансово обезпечение с дългови ценни книжа, приети за търговия на български регулиран пазар или на регулирани пазари на ценни книжа в държави – членки на Европейския съюз;\n9. обезпеченията по чл. 152, ал. 8 под формата на финансово обезпечение по смисъла на Закона за договорите за финансово обезпечение с инструменти на собствения капитал, приети за търговия на български регулиран пазар или на регулирани пазари на ценни книжа в държави – членки на Европейския съюз;\n10. обезпеченията по чл. 152, ал. 8 под формата на финансово обезпечение по смисъла на Закона за договорите за финансово обезпечение с други дългови ценни книжа;\n11. други обезпечения по чл. 152, ал. 8.\n(11) В случай на превишение на стойността на активите, които служат като обезпечение, над размера на вземането по ал. 1 с натрупаната лихва, в масата на несъстоятелността се връща частта от активите, съответстваща на превишението според поредността по ал. 10, и/или парични средства, както следва:\n1. за обезпеченията по ал. 10, т. 1 – 10 и по ал. 14 – в 60-дневен срок от деня на обявяване на банката в несъстоятелност;\n2. за останалите обезпечения по ал. 10, т. 11 – в 60-дневен срок от окончателното определяне на стойността на активите, които служат като обезпечения.\n(12) В случай че определената по реда на ал. 13 стойност на активите, които служат като обезпечение, е по-малка от размера на вземането по ал. 1 заедно с натрупаната лихва, за остатъка държавата участва като кредитор в разпределението на осребреното имущество в производството по несъстоятелност на банката заедно с кредиторите по чл. 94, ал. 1, т. 8 от Закона за банковата несъстоятелност и се представлява от Националната агенция за приходите.\n(13) За целите на прилагане на ал. 10 – 12 стойността на активите, които служат като обезпечения по чл. 152, ал. 2 – 6, както и на активите по ал. 10, т. 5 – 10, се определя съгласно указанията по чл. 152, ал. 13.\n(14) За активите, които служат като обезпечения по чл. 152, ал. 8 под формата на залог на вземания, за целите на ал. 10 – 12 се прилага определената съгласно указанията по чл. 152, ал. 13 стойност, когато тя е в размер на номиналната стойност на вземанията.\n(15) За целите на прилагане на ал. 10 – 12 стойността на активите, които служат като обезпечения по чл. 152, ал. 8, без тези по ал. 10, т. 5 – 10 и ал. 14, се определя към датата на обявяване на банката в несъстоятелност от независим оценител. Оценката е окончателна и не подлежи на обжалване. Изборът на независимия оценител се извършва по ред, определен от министъра на финансите и от управителя на Българската народна банка с указанията по чл. 152, ал. 13.\n(16) Доколкото с акт на Министерския съвет не е определено друго, активите по ал. 10, останали под разпореждането на министъра на финансите след прилагането на ал. 11 – 15, преминават в собственост на държавата, включват се в обхвата на активите за целите на управление на ликвидността на единната сметка съгласно чл. 154, ал. 22 и се реализират от министъра на финансите, като съответните държавни ценни книжа могат да се продават или използват за други операции на вторичния пазар, да се канцелират или да се държат до техния падеж.\n(17) С акт на Министерския съвет се определя срок за възстановяване на средствата на бюджетните организации по ал. 1 от централния бюджет, който не може да е по-дълъг от четири месеца от датата на обявяване на банката в несъстоятелност.\n(18) При падеж или изплащане на лихви по държавни ценни книжа и други дългови инструменти, които са преминали под пълно разпореждане на министъра на финансите съгласно чл. 152, ал. 9, изплатените суми постъпват в полза на централния бюджет.\n(19) При обявяване на банка в несъстоятелност и в изпълнение на чл. 152, ал. 9 Българската народна банка:\n1. служебно прехвърля по открити при нея партиди/сметки на Министерството на финансите всички държавни ценни книжа на банката в несъстоятелност, блокирани като обезпечение по чл. 152, ал. 3 и 4;\n2. служебно превежда по посочени от министъра на финансите сметки на централния бюджет средствата от обезпеченията по чл. 152, ал. 5 и 6 в пълен размер.\n(20) Министърът на финансите дава указания по прилагането на ал. 1 – 19."
    },
    {
      "provision_ref": "152в",
      "section": "152в",
      "title": "Чл. 152в.",
      "content": "Чл. 152в. (1) Средства по подлежащи на обезпечаване съгласно чл. 152, ал. 1 сметки и депозити на бюджетни организации в банка, която е в режим на преструктуриране, включително чрез държавни инструменти за финансова стабилизация, в банка, поставена под специален надзор, или в банка, на която е отнет лицензът за банкова дейност, могат да се възстановяват на бюджетните организации в левове за сметка на средства на централния бюджет в Българската народна банка при условията и по реда на ал. 2 – 5 въз основа на акт на Министерския съвет.\n(2) С акта на Министерския съвет се определя и срокът за възстановяване на средствата на бюджетните организации по ал. 1 от централния бюджет.\n(3) Въз основа на акта на Министерския съвет и уведомление от министъра на финансите съответната банка прехвърля средствата на бюджетните организации по ал. 1 по открита при нея сметка на централния бюджет с титуляр – Министерството на финансите, при запазване на съответните обезпечения по чл. 152 и закрива съответните сметки и депозити на бюджетните организации.\n(4) Възстановяването на средствата по ал. 1 се извършва и отчита по реда на чл. 152б, ал. 2 – 7.\n(5) За предоставянето на информация и уточняване на размера на средствата по текущи и депозитни сметки на бюджетните организации по ал. 1 се прилагат изискванията на чл. 152б, ал. 8 и 9.\n(6) В случай че банка, на която е бил отнет лицензът за банкова дейност, бъде обявена в несъстоятелност, се прилага чл. 152б.\n(7) В случай на ликвидация на банка се прилага редът по чл. 152, ал. 9 и чл. 152б.\n(8) Министърът на финансите дава указания по прилагането на ал. 1 – 7."
    },
    {
      "provision_ref": "152г",
      "section": "152г",
      "title": "Чл. 152г.",
      "content": "Чл. 152г. При прилагането на чл. 152 и чл. 152а – 152в разпоредбите на глави седма и осма от Закона за особените залози, както и на чл. 152 и чл. 156, ал. 2 от Закона за задълженията и договорите не се прилагат.“\n§ 30. В чл. 153, ал. 10 накрая се добавя „както и средства от Европейския съюз и свързаното с тях национално съфинансиране на лицата по чл. 156, независимо дали останалите им средства са включени в единната сметка“.\n§ 31. В чл. 154 се правят следните изменения и допълнения:\n1. В ал. 9 изречение първо се изменя така: „Обслужването от банките в страната на плащанията чрез СЕБРА и на транзитните сметки по ал. 4 – 8 се извършва въз основа на сключени договори между Министерството на финансите и банките, като в тях може да се включва и обслужване на операции на бюджетните организации по събирането на приходи и други постъпления чрез картови плащания.“\n2. В ал. 12, изречение първо думите „от името и за сметка на Министерството на финансите“ се заменят с „от името на Министерството на финансите и за сметка на централния бюджет“.\n3. Алинея 14 се изменя така:\n„(14) За сметки за чужди средства, сметки за средства от Европейския съюз, както и за бюджети на първостепенни разпоредители с бюджет, които не са част от държавния бюджет, министърът на финансите може да определи техните лимити да се определят автоматично на базата на общия размер на постъпленията по съответната сметка в Българската народна банка.“\n4. В ал. 20, изречение второ думите „от името и за сметка на Министерството на финансите“ се заменят с „от името на Министерството на финансите и за сметка на централния бюджет“.\n5. Алинеи 22 и 23 се изменят така:\n„(22) Министърът на финансите упражнява общ контрол, осъществява управление на ликвидността и се разпорежда със средствата в единната сметка, включително чрез извършване на депозити в Българската народна банка и в банките, на операции на вторичния пазар с държавни ценни книжа, на операции със заеми на Българската народна банка и ценни книжа, емитирани от нея, както и на други операции с ликвидни и нискорискови ценни книжа на други държави, с активите по чл. 152б, ал. 16 и с активите, преминали в собственост на държавата при прилагането на чл. 152в, ал. 7. При определяне на общите насоки за управление на ликвидността Министерството на финансите провежда консултации с Българската народна банка.\n(23) Въз основа на акт на Министерския съвет министърът на финансите може да извършва, освен в случаите по ал. 22, гаранционни и други депозити в банки за целите на финансиране чрез банки на проекти по международни програми и договори и за други цели и плащания, както и да придобива от името на държавата финансови активи при прилагане на държавни инструменти за финансова стабилизация и предоставяне на извънредна публична финансова подкрепа.“\n6. Създава се ал. 24:\n„(24) Операциите по ал. 22 и 23 се извършват в рамките на общата наличност на единната сметка чрез сметки на централния бюджет при осигуряване на текущите плащания на централния бюджет и включените в единната сметка и СЕБРА бюджетни организации и лица по чл. 156.“\n§ 32. В § 1 от допълнителните разпоредби се правят следните изменения и допълнения:\n1. Създава се т. 24а:\n„24а. „Основни бюджетни взаимоотношения между общинските бюджети и централния бюджет“ са трансферите по бюджетите на общините по чл. 52, ал. 1, т. 1, букви „а“, „б“ и „в“, приети със закона за държавния бюджет за съответната година.“\n2. В т. 33 думите „чл. 79 от“ се заличават.\n3. В т. 41, буква „г“ накрая се добавя „и 23“.\nЗаключителни разпоредби\n§ 33. В Закона за Икономически и социален съвет (обн., ДВ, бр. 41 от 2001 г.; изм., бр. 120 от 2002 г., бр. 20 от 2003 г., бр. 17 от 2006 г., бр. 36 от 2008 г., бр. 82 от 2009 г., бр. 14 и 61 от 2015 г. и бр. 98 от 2016 г.) в чл. 21, ал. 2 думите „Закона за устройството на държавния бюджет“ се заменят със „Закона за публичните финанси“.\n§ 34. В Закона за физическото възпитание и спорта (обн., ДВ, бр. 58 от 1996 г.; Решение № 8 на Конституционния съд на РБ от 1997 г. – бр. 53 от 1997 г.; изм., бр. 124 от 1998 г., бр. 51 и 81 от 1999 г., бр. 53, 55 и 64 от 2000 г., бр. 75 от 2002 г.; Решение № 6 на Конституционния съд на РБ от 2002 г. – бр. 95 от 2002 г.; изм., бр. 120 от 2002 г., бр. 96 от 2004 г., бр. 88 и 103 от 2005 г., бр. 30, 34, 36 и 80 от 2006 г., бр. 41, 46 и 53 от 2007 г., бр. 50 от 2008 г., бр. 74 от 2009 г., бр. 50 и 96 от 2010 г., бр. 35 и 99 от 2011 г., бр. 45, 87 и 102 от 2012 г., бр. 15 и 68 от 2013 г., бр. 21 и 66 от 2014 г., бр. 14, 61, 79 и 101 от 2015 г. и бр. 43 от 2016 г.) в чл. 41б, т. 1 думата „републиканския“ се заменя с „държавния“.\n§ 35. В Закона за кооперациите (обн., ДВ, бр. 113 от 1999 г.; изм., бр. 92 от 2000 г., бр. 98 от 2001 г., бр. 13 от 2003 г., бр. 102 и 105 от 2005 г., бр. 33, 34, 80 и 105 от 2006 г., бр. 41, 53 и 104 от 2007 г. и бр. 43 от 2008 г.) в чл. 63, ал. 5 думите „извънбюджетни сметки или фондове“ се заличават.\n§ 36. В Закона за отнемане в полза на държавата на незаконно придобито имущество (обн., ДВ, бр. 38 от 2012 г.; Решение № 13 на Конституционния съд на РБ от 2012 г. – бр. 82 от 2012 г.; изм., бр. 102 и 103 от 2012 г., бр. 15 от 2013 г.; Решение № 2 от 2013 г. на Конституционния съд на РБ – бр. 50 от 2013 г.; изм., бр. 66 от 2013 г., бр. 98 от 2014 г., бр. 14, 22, 74 и 95 от 2015 г., бр. 103 от 2016 г. и бр. 58 от 2017 г.) в чл. 90 ал. 5 се отменя.\n§ 37. В Закона за банковата несъстоятелност (обн., ДВ, бр. 92 от 2002 г.; изм., бр. 67 от 2003 г., бр. 36 от 2004 г., бр. 31 и 105 от 2005 г., бр. 30, 34, 59 и 80 от 2006 г., бр. 53 и 59 от 2007 г., бр. 67 от 2008 г., бр. 105 от 2011 г., бр. 98 от 2014 г., бр. 22, 41, 50, 61, 62 и 94 от 2015 г. и бр. 33 и 95 от 2016 г.) се правят следните допълнения:\n1. В чл. 3, ал. 1, т. 1 накрая се добавя „с изключение на активите по чл. 152, ал. 9 от Закона за публичните финанси“.\n2. В чл. 63, ал. 3, изречение първо след думата „несъстоятелност“ се добавя „вземанията на Министерството на финансите по чл. 152б, ал. 1 от Закона за публичните финанси“.\n§ 38. В Закона за Държавния фонд за гарантиране устойчивост на държавната пенсионна система (обн., ДВ, бр. 98 от 2008 г.; изм., бр. 99 от 2009 г., бр. 15 от 2013 г. и бр. 61 от 2015 г.) се правят следните изменения и допълнения:\n1. В чл. 13:\nа) в ал. 1 т. 1 се изменя така:\n„1. депозити и сметки в Българската народна банка, нейни заеми и ценни книжа, емитирани от нея;“\nб) създават се ал. 11 – 14:\n„(11) Управлението на активите на фонда по ал. 1, т. 1, включително разпределението им по текущи, депозитни и други сметки, се извършва от министъра на финансите за оптимизиране на касовото управление на средствата във фискалния резерв.\n(12) В случай че активи на фонда по ал. 1, т. 1 са с отрицателна лихва/доходност, тя е за сметка на централния бюджет.\n(13) За средствата на фонда, съхранявани по текущи сметки, обслужвани от Българската народна банка, се изчислява в полза на фонда и за сметка на централния бюджет доходност в размер на приложимата за съответния период лихва по депозитни сметки, обслужвани от Българската народна банка, при спазване на изискванията на ал. 12. Изчислената сума се превежда по реда на чл. 11, ал. 3.\n(14) Разходите за обслужване на сметките на фонда са изцяло за сметка на централния бюджет.“\n2. В чл. 22:\nа) в ал. 4 думите „ал. 2 и 6“ се заменят с „ал. 2, 6 и 7“;\nб) създава се ал. 7:\n„(7) Паричните постъпления, произтичащи от активи по чл. 11, ал. 5 и чл. 13, ал. 9, се внасят и отчитат по сметките на фонда в Българската народна банка по реда на чл. 11, ал. 3, доколкото в закон или с акт на Министерския съвет не е определено друго.“\n§ 39. В Закона за публичното предлагане на ценни книжа (обн., ДВ, бр. 114 от 1999 г.; изм., бр. 63 и 92 от 2000 г., бр. 28, 61, 93 и 101 от 2002 г., бр. 8, 31, 67 и 71 от 2003 г., бр. 37 от 2004 г., бр. 19, 31, 39, 103 и 105 от 2005 г., бр. 30, 33, 34, 59, 63, 80, 84, 86 и 105 от 2006 г., бр. 25, 52, 53 и 109 от 2007 г., бр. 67 и 69 от 2008 г., бр. 23, 24, 42 и 93 от 2009 г., бр. 43 и 101 от 2010 г., бр. 57 и 77 от 2011 г., бр. 21, 94 и 103 от 2012 г., бр. 109 от 2013 г., бр. 34, 61, 62, 95 и 102 от 2015 г., бр. 33, 42, 62 и 76 от 2016 г. и бр. 62 от 2017 г.) в чл. 2, ал. 1 в текста преди т. 1 след думите „а за държавните ценни книжа“ се добавя „и за ценни книжа, емитирани от Българската народна банка“.\n§ 40. В Закона за държавния дълг (обн., ДВ, бр. 93 от 2002 г.; изм., бр. 34 от 2005 г., бр. 52 от 2007 г., бр. 23 от 2009 г., бр. 101 от 2010 г., бр. 99 от 2011 г., бр. 103 от 2012 г., бр. 15 от 2013, бр. 50 от 2015 г. и бр. 43 и 98 от 2016 г.) се правят следните допълнения:\n1. В чл. 5, ал. 1 се създава т. 7:\n„7. за финансиране на програми и инструменти за финансова стабилизация и предоставяне на извънредна публична финансова подкрепа по Закона за възстановяване и преструктуриране на кредитни институции и инвестиционни посредници.“\n2. В чл. 29 се създава изречение второ: „Българската народна банка определя с наредба условията и реда за придобиване, изплащане, търговия и сетълмент с емитирани от нея ценни книжа.“\n§ 41. В Закона за възстановяване и преструктуриране на кредитни институции и инвестиционни посредници (обн., ДВ, бр. 62 от 2015 г.; изм., бр. 59 от 2016 г. и бр. 85 от 2017 г.) в чл. 51 се правят следните изменения и допълнения:\n1. В ал. 1, т. 3 думите „ал. 5“ се заменят с „ал. 7“.\n2. Създава се нова ал. 5:\n„(5) Подкрепата по ал. 3, т. 4, букви „а“ и „б“ се предоставя по решение на Министерския съвет при спазване на Закона за държавните помощи и правната рамка на Европейския съюз за държавната помощ и след постановяване на положително решение от страна на Европейската комисия, въз основа на мотивирано предложение от Българската народна банка до министъра на финансите, в което се съдържа подробна информация за изпълнението на условията по ал. 4 и за другите обстоятелства от значение за предоставянето на помощта.“\n3. Създава се ал. 6:\n„(6) С решението по ал. 5 Министерският съвет определя конкретната форма и размера на извънредната публична финансова подкрепа, както и други условия, които следва да се изпълнят, и мерки, които следва да се приложат. Министърът на финансите отговаря за изпълнението на решението на Министерския съвет.“\n4. Досегашната ал. 5 става ал. 7.\nЗаконът е приет от 44-то Народно събрание на 1 ноември 2017 г. и е подпечатан с официалния печат на Народното събрание.\nПредседател на Народното събрание: Димитър Главчев\n8444"
    }
  ],
  "definitions": []
}