{
  "id": "act-163440",
  "type": "statute",
  "title": "Закон за ратифициране на Спогодбата между Република България и Кралство Нидерландия за избягване на двойното данъчно облагане с данъци на доходите и предотвратяване на отклонението и заобикалянето на данъчно облагане",
  "short_name": "002-02-20",
  "status": "in_force",
  "issued_date": "2020-11-27",
  "in_force_date": "2021-01-14",
  "url": "https://www.parliament.bg/bg/laws/ID/163440",
  "description": "Official promulgated act published by the National Assembly of the Republic of Bulgaria (act ID 163440).",
  "provisions": [
    {
      "provision_ref": "body",
      "section": "body",
      "title": "Основен текст",
      "content": "УКАЗ № 13\nНа основание чл. 98, т. 4 от Конституцията на Република България\nПОСТАНОВЯВАМ:\nДа се обнародва в „Държавен вестник“ Законът за ратифициране на Спогодбата между Република България и Кралство Нидерландия за избягване на двойното данъчно облагане с данъци на доходите и предотвратяване на отклонението и заобикалянето на данъчно облагане, приет от 44-то Народно събрание на 14 януари 2021 г.\nИздаден в София на 18 януари 2021 г.\nПрезидент на Републиката: Румен Радев\nПодпечатан с държавния печат.\nМинистър на правосъдието: Десислава Ахладова\nЗАКОН\nза ратифициране на Спогодбата между Република България и Кралство Нидерландия за избягване на двойното данъчно облагане с данъци на доходите и предотвратяване на отклонението и заобикалянето на данъчно облагане\nЧлен единствен. Ратифицира Спогодбата между Република България и Кралство Нидерландия за избягване на двойното данъчно облагане с данъци на доходите и предотвратяване на отклонението и заобикалянето на данъчно облагане, подписана на 14 септември 2020 г. в София.\nЗаконът е приет от 44-то Народно събрание на 14 януари 2021 г. и е подпечатан с официалния печат на Народното събрание.\nПредседател на Народното събрание: Цвета Караянчева\n281"
    }
  ],
  "definitions": []
}