{
  "id": "act-163713",
  "type": "statute",
  "title": "Закон за изменение и допълнение на Закона за бюджета на държавното обществено осигуряване за 2021 г.",
  "short_name": "46-102-01-2",
  "status": "in_force",
  "issued_date": "2021-07-30",
  "in_force_date": "2021-09-09",
  "url": "https://www.parliament.bg/bg/laws/ID/163713",
  "description": "Official promulgated act published by the National Assembly of the Republic of Bulgaria (act ID 163713).",
  "provisions": [
    {
      "provision_ref": "body",
      "section": "body",
      "title": "Основен текст",
      "content": "УКАЗ № 241\nНа основание чл. 98, т. 4 от Конституцията на Република България\nПОСТАНОВЯВАМ:\nДа се обнародва в „Държавен вестник“ Законът за изменение и допълнение на Закона за бюджета на държавното обществено осигуряване за 2021 г., приет от 46-ото Народно събрание на 9 септември 2021 г.\nИздаден в София на 14 септември 2021 г.\nПрезидент на Републиката: Румен Радев\nПодпечатан с държавния печат.\nМинистър на правосъдието: Янаки Стоилов\nЗАКОН\nза изменение и допълнение на Закона за бюджета на държавното обществено осигуряване за 2021 г. (обн., ДВ, бр. 103 от 2020 г.; изм., бр. 107 от 2020 г.)\n§ 1. Член 1 се изменя така:\n„Чл. 1. (1) Приема консолидирания бюджет на държавното обществено осигуряване по приходите и трансферите на обща сума 15 566 455,5 хил. лв., както следва:\nП О К А З А Т Е Л И\nСума\n(хил. лв.)\nІ.\nПРИХОДИ И ТРАНСФЕРИ – ВСИЧКО\n15 566 455,5\n1.\nОсигурителни приходи\n8 877 110,3\n1.1.\nОсигурителни вноски\n8 877 110,3\n2.\nНеданъчни приходи\n186 730,0\n2.1.\nПриходи и доходи от собственост\n5 600,0\n2.2.\nГлоби, санкции и наказателни лихви\n23 900,0\n2.3.\nДруги приходи\n157 230,0\n3.\nВнесени ДДС и други данъци върху продажбите\n-1 040,0\n4.\nПолучени трансфери от централния бюджет за държавното обществено осигуряване\n178 643,3\n5.\nПолучени допълнителни трансфери от централния/държавния бюджет за покриване на недостига от средства\n6 325 011,9\n(2) Приема консолидирания бюджет на държавното обществено осигуряване по разходите и трансферите на обща сума 15 566 455,5 хил. лв., както следва:\nІ.\nРАЗХОДИ И ТРАНСФЕРИ – ВСИЧКО\n15 566 455,5\n1.\nРазходи\n15 559 055,5\n1.1.\nПенсии\n13 047 933,4\n1.1.1.\nПенсии за сметка на държавното обществено осигуряване\n12 869 140,2\n1.1.2.\nПенсии за сметка на държавния бюджет\n177 593,2\n1.1.3.\nКапиталов трансфер за прехвърляне на пенсионни права към пенсионните схеми на ЕС, ЕЦБ и ЕИБ\n1 200,0\n1.2.\nСоциални помощи и обезщетения\n2 063 654,9\n1.3.\nПрограми, дейности и служби по социалното осигуряване, подпомагане и заетостта\n447 275,0\n1.3.1.\nРазходи за персонал\n91 747,6\n1.3.2.\nИздръжка\n48 290,0\n1.3.3.\nПлатени данъци, такси и административни санкции\n550,0\n1.3.4.\nРазходи за членски внос и участие в нетърговски организации и дейности\n148,2\n1.3.5.\nКапиталови разходи\n6 539,2\n1.3.6.\nДруги програми и дейности за осигуряване на заетост\n300 000,0\n1.4.\nОтбрана и сигурност\n192,2\n2.\nПредоставени трансфери\n7 400,0\n2.1.\nНа Министерството на здравеопазването съгласно чл. 11, ал. 1, т. 2, буква „в“, чл. 12, ал. 1, т. 4 и чл. 13, ал. 1, т. 3 от Кодекса за социално осигуряване\n3 150,0\n2.2.\nНа Министерството на труда и социалната политика за фонд „Условия на труд“\n4 000,0\n2.2.1.\nМероприятия за предотвратяване на трудовите злополуки и професионалните болести съгласно чл. 24, т. 3 от Кодекса за социално осигуряване\n3 000,0\n2.2.2.\nЗа диагностика на професионалните болести съгласно чл. 24, т. 4 от Кодекса за социално осигуряване\n1 000,0\n2.3.\nНа Министерството на транспорта, информационните технологии и съобщенията съгласно чл. 92, ал. 4 от НПОС\n250,0\n(3) Приема дефицит (излишък) и финансиране по бюджета на държавното обществено осигуряване, както следва:\nДЕФИЦИТ /-/ , ИЗЛИШЪК /+/\n0,0\n“\n§ 2. Член 2 се изменя така:\n„Чл. 2. (1) Приема бюджета на фонд „Пенсии“ по приходите и трансферите на обща сума 6 298 154,5 хил. лв., както следва:\nІ .\nПРИХОДИ И ТРАНСФЕРИ – ВСИЧКО\n6 298 154,5\n1.\nОсигурителни приходи\n6 194 504,4\n1.1.\nОсигурителни вноски\n6 194 504,4\n2.3.\nДруги приходи\n103 000,0\n4.\nПолучени трансфери от централния бюджет за държавното обществено осигуряване\n650,1\n(2) Приема бюджета на фонд „Пенсии“ по разходите и трансферите на обща сума 11 877 056,4 хил. лв., както следва:\nІ. РАЗХОДИ И ТРАНСФЕРИ – ВСИЧКО\n11 877 056,4\n1. Разходи\n11 877 056,4\n1.1. Пенсии\n11 876 523,5\n1.1.1. Пенсии за сметка на държавното обществено осигуряване\n11 875 323,5\n1.1.3. Капиталов трансфер за прехвърляне на пенсионни права към пенсионните схемина ЕС, ЕЦБ и ЕИБ\n1 200,0\n1.2. Социални помощи и обезщетения\n532,9\n(3) Приема дефицит (излишък) по бюджета на фонд „Пенсии“, както следва:\nДЕФИЦИТ /-/ , ИЗЛИШЪК /+/\n-5 578 901,9\n“\n§ 3. Член 3 се изменя така:\n„Чл. 3. (1) Приема бюджета на фонд „Пенсии за лицата по чл. 69“ по приходите и трансферите на обща сума 766 791,9 хил. лв., както следва:\nІ. ПРИХОДИ И ТРАНСФЕРИ – ВСИЧКО\n766 791,9\n1. Осигурителни приходи\n766 791,9\n1.1. Осигурителни вноски\n766 791,9\n(2) Приема бюджета на фонд „Пенсии за лицата по чл. 69“ по разходите и трансферите на обща сума 948 955,1 хил. лв., както следва:\nІ. РАЗХОДИ И ТРАНСФЕРИ – ВСИЧКО\n948 955,1\n1. Разходи\n948 955,1\n1.1. Пенсии\n948 953,5\n1.1.1. Пенсии за сметка на държавното обществено осигуряване\n948 953,5\n1.2. Социални помощи и обезщетения\n1,6\n(3) Приема дефицит (излишък) по бюджета на фонд „Пенсии за лицата по чл. 69“, както следва:\nДЕФИЦИТ /-/ , ИЗЛИШЪК /+/\n-182 163,2\n“\n§ 4. Член 4 се изменя така:\n„Чл. 4. (1) Приема бюджета на фонд „Пенсии, несвързани с трудова дейност“ по приходите и трансферите на обща сума 177 593,2 хил. лв., както следва:\nІ. ПРИХОДИ И ТРАНСФЕРИ – ВСИЧКО\n177 593,2\n4. Получени трансфери от централния бюджет за държавното обществено осигуряване\n177 593,2\n(2) Приема разходи и трансфери (субсидии, вноски) между държавния бюджет и бюджета на фонд „Пенсии, несвързани с трудова дейност“ на обща сума 177 610,7 хил. лв., както следва:\nІ. РАЗХОДИ И ТРАНСФЕРИ – ВСИЧКО\n177 610,7\n1. Разходи\n177 610,7\n1.1. Пенсии\n177 593,2\n1.1.2. Пенсии за сметка на държавния бюджет\n177 593,2\n1.2. Социални помощи и обезщетения\n17,5\n(3) Приема дефицит (излишък) по бюджета на фонд „Пенсии, несвързани с трудова дейност“, както следва:\nДЕФИЦИТ /-/ , ИЗЛИШЪК /+/\n-17,5\n“\n§ 5. Член 5 се изменя така:\n„Чл. 5. (1) Приема бюджета на фонд „Трудова злополука и професионална болест“ по приходите и трансферите на обща сума 245 893,1 хил. лв., както следва:\nІ. ПРИХОДИ И ТРАНСФЕРИ – ВСИЧКО\n245 893,1\n1. Осигурителни приходи\n245 893,1\n1.1. Осигурителни вноски\n245 893,1\n(2) Приема бюджета на фонд „Трудова злополука и професионална болест“ по разходите и трансферите на обща сума 62 494,3 хил. лв., както следва:\nІ. РАЗХОДИ И ТРАНСФЕРИ – ВСИЧКО\n62 494,3\n1. Разходи\n58 144,3\n1.1. Пенсии\n44 863,2\n1.1.1. Пенсии за сметка на държавното обществено осигуряване\n44 863,2\n1.2. Социални помощи и обезщетения\n13 281,1\n2. Предоставени трансфери\n4 350,0\n2.1. На Министерството на здравеопазването съгласно чл. 24, т. 5 от Кодекса засоциално осигуряване\n350,0\n2.2. На Министерството на труда и социалната политика за фонд „Условия на труд“\n4 000,0\n2.2.1. Мероприятия за предотвратяване на трудовите злополуки и професионалнитеболести съгласно чл. 24, т. 3 от Кодекса за социално осигуряване\n3 000,0\n2.2.2. За диагностика на професионалните болести съгласно чл. 24, т. 4 от Кодекса за социално осигуряване\n1 000,0\n(3) Приема дефицит (излишък) по бюджета на фонд „Трудова злополука и професионална болест“, както следва:\nДЕФИЦИТ /-/ , ИЗЛИШЪК /+/\n183 398,8\n“\n§ 6. Член 6 се изменя така:\n„Чл. 6. (1) Приема бюджета на фонд „Общо заболяване и майчинство“ по приходите и трансферите на обща сума 1 304 813,2 хил. лв., както следва:\nІ. ПРИХОДИ И ТРАНСФЕРИ – ВСИЧКО\n1 304 813,2\n1. Осигурителни приходи\n1 304 813,2\n1.1. Осигурителни вноски\n1 304 813,2\n(2) Приема бюджета на фонд „Общо заболяване и майчинство“ по разходите и трансферите на обща сума 1 341 010,3 хил. лв., както следва:\nІ. РАЗХОДИ И ТРАНСФЕРИ – ВСИЧКО\n1 341 010,3\n1. Разходи\n1 338 210,3\n1.2. Социални помощи и обезщетения\n1 338 210,3\n2. Предоставени трансфери\n2 800,0\n2.1.На Министерството на здравеопазването съгласно чл. 26, т. 4 от Кодекса за социално осигуряване\n2 800,0\n(3) Приема дефицит (излишък) по бюджета на фонд „Общо заболяване и майчинство“, както следва:\nДЕФИЦИТ /-/ , ИЗЛИШЪК /+/\n-36 197,1\n“\n§ 7. Член 7 се изменя така:\n„Чл. 7. (1) Приема бюджета на фонд „Безработица“ по приходите и трансферите на обща сума 365 507,7 хил. лв., както следва:\nІ. ПРИХОДИ И ТРАНСФЕРИ – ВСИЧКО\n365 507,7\n1. Осигурителни приходи\n365 107,7\n1.1. Осигурителни вноски\n365 107,7\n4. Получени трансфери от централния бюджет за държавното обществено осигуряване\n400,0\n(2) Приема бюджета на фонд „Безработица“ по разходите и трансферите на обща сума 711 611,5 хил. лв., както следва:\nІ. РАЗХОДИ И ТРАНСФЕРИ – ВСИЧКО\n711 611,5\n1. Разходи\n711 611,5\n1.2. Социални помощи и обезщетения\n711 611,5\n(3) Приема дефицит (излишък) по бюджета на фонд „Безработица“, както следва:\nДЕФИЦИТ /-/ , ИЗЛИШЪК /+/\n-346 103,8\n“\n§ 8. Член 8 се изменя така:\n„Чл. 8. (1) Приема бюджета на Националния осигурителен институт по приходите и трансферите на обща сума 6 407 701,9 хил. лв., както следва:\nІ. ПРИХОДИ И ТРАНСФЕРИ – ВСИЧКО\n6 407 701,9\n2. Неданъчни приходи\n83 730,0\n2.1. Приходи и доходи от собственост\n5 600,0\n2.2. Глоби, санкции и наказателни лихви\n23 900,0\n2.3. Други приходи\n54 230,0\n3. Внесени ДДС и други данъци върху продажбите\n-1 040,0\n5. Получени допълнителни трансфери от централния/държавния бюджет за покриване на недостига от средства\n6 325 011,9\n(2) Приема бюджета на Националния осигурителен институт по разходите и трансферите на обща сума 447 717,2 хил. лв., както следва:\nІ. РАЗХОДИ И ТРАНСФЕРИ – ВСИЧКО\n447 717,2\n1. Разходи\n447 467,2\n1.3. Програми, дейности и служби по социалното осигуряване, подпомагане и заетостта\n447 275,0\n1.3.1. Разходи за персонал\n91 747,6\n1.3.2. Издръжка\n48 290,0\n1.3.3. Платени данъци, такси и административни санкции\n550,0\n1.3.4. Разходи за членски внос и участие в нетърговски организации и дейности\n148,2\n1.3.5. Капиталови разходи\n6 539,2\n1.3.6. Други програми и дейности за осигуряване на заетост\n300 000,0\n1.4. Отбрана и сигурност\n192,2\n2. Предоставени трансфери\n250,0\n2.3. На Министерството на транспорта, информационните технологии и съобщенията\nсъгласно чл. 92, ал. 4 от НПОС\n250,0\n(3) Приема дефицит (излишък) по бюджета на Националния осигурителен институт, както следва:\nДЕФИЦИТ /-/ , ИЗЛИШЪК /+/\n5 959 984,7\n“\n§ 9. Член 10 се изменя така:\n„Чл. 10. Определя се следният минимален размер на пенсията за осигурителен стаж и възраст по чл. 68, ал. 1 от Кодекса за социално осигуряване за 2021 г.:\n1. от 1 януари до 24 декември – 300 лв.;\n2. от 25 декември – 370 лв.“\n§ 10. В чл. 12 след думите „2021 г.“ се поставя запетая и думите „- 380 лв.“ се заменят с „както следва:\n1. от 1 януари до 30 септември – 380 лв.;\n2. от 1 октомври до 31 декември – 650 лв.“\n§ 11. В преходните и заключителните разпоредби се правят следните изменения и допълнения:\n1. В § 6:\nа) в ал. 1 думите „февруари и март“ се заменят с „февруари, март и септември“;\nб) създава се нова ал. 2:\n„(2) Към пенсията или сбора от пенсиите, заедно с добавките и компенсациите към тях на всеки пенсионер за месеците октомври, ноември и декември 2021 г. се изплаща допълнителна сума в размер на 120 лв.“;\nв) досегашната ал. 2 става ал. 3 и в нея думите „ал. 1“ се заменят с „ал. 1 и 2“.\n2. В § 7 ал. 2 се изменя така:\n„(2) За 2021 г. максималният размер на получаваните една или повече пенсии без добавките към тях се определя, както следва:\n1. от 1 януари до 24 декември – 1440 лв.;\n2. от 25 декември – 1500 лв.“\n§ 12. Приложение № 5 към чл. 17 се изменя така:\n„Приложение № 5 към чл. 17\nКОНСОЛИДИРАН БЮДЖЕТ\nна администрираните от Националния осигурителен институт социалноосигурителни фондове за 2021 г.\nП О К А З А Т Е Л И\nСума\n(хил. лв.)\nІ. ПРИХОДИ И ТРАНСФЕРИ – ВСИЧКО\n15 656 739 , 9\n1. Приходи\n9 153 084 , 7\n1.1. Осигурителни приходи\n8 957 434 , 5\n1.1.1. Осигурителни вноски\n8 957 434 , 5\n1.2. Неданъчни приходи\n196 690 , 2\n1.3. Внесени ДДС и други данъци върху продажбите\n-1 040 , 0\n2. Получени трансфери от централния/държавния бюджет\n6 503 655 , 2\nIІ. РАЗХОДИ И ТРАНСФЕРИ – ВСИЧКО\n15 629 281,8\n1. Разходи\n15 621 881 , 8\n1.1. Пенсии\n13 105 941 , 8\n1.2. Социални помощи и обезщетения\n2 068 154 , 9\n1.3. Програми, дейности и служби по социалното осигуряване, подпомагане и заетостта\n447 592 , 9\n1.3.1. Разходи за персонал\n91 870 , 1\n1.3.2. Издръжка\n48 485 , 4\n1.3.3. Платени данъци, такси и административни санкции\n550 , 0\n1.3.4. Разходи за членски внос и участие в нетърговски организации и дейности\n148 , 2\n1.3.5. Капиталови разходи\n6 539 , 2\n1.3.6. Други програми и дейности за осигуряване на заетост\n300 000 , 0\n1.4. Отбрана и сигурност\n192 , 2\n2. Предоставени трансфери\n7 400 , 0\nДЕФИЦИТ /-/ , ИЗЛИШЪК /+/\n27 458 , 1\nФИНАНСИРАНЕ\n-27 458 , 1\nПокупка-продажба на държавни (общински) ценни книжа – нето (+/-)\n-5 609 , 5\nДепозити и средства по сметки – нето (+/-)\n-21 848 , 6\nНаличности в началото на периода (+)\n97 374 , 6\nНаличности в края на периода (-)\n-119 223 , 2\nПогашения по дългосрочни заеми от банки и финансови институции от чужбина (-)\n-\n“\nЗаключителни разпоредби\n§ 13. В Кодекса за социално осигуряване (обн., ДВ, бр. 110 от 1999 г.; Решение № 5 на Конституционния съд от 2000 г. – бр. 55 от 2000 г.; изм., бр. 64 от 2000 г., бр. 1, 35 и 41 от 2001 г., бр. 1, 10, 45, 74, 112, 119 и 120 от 2002 г., бр. 8, 42, 67, 95, 112 и 114 от 2003 г., бр. 12, 21, 38, 52, 53, 69, 70, 112 и 115 от 2004 г., бр. 38, 39, 76, 102, 103, 104 и 105 от 2005 г., бр. 17, 30, 34, 56, 57, 59 и 68 от 2006 г.; попр., бр. 76 от 2006 г.; изм., бр. 80, 82, 95, 102 и 105 от 2006 г., бр. 41, 52, 53, 64, 77, 97, 100, 109 и 113 от 2007 г., бр. 33, 43, 67, 69, 89, 102 и 109 от 2008 г., бр. 23, 25, 35, 41, 42, 93, 95, 99 и 103 от 2009 г., бр. 16, 19, 43, 49, 58, 59, 88, 97, 98 и 100 от 2010 г.; Решение № 7 на Конституционния съд от 2011 г. – бр. 45 от 2011 г.; изм., бр. 60, 77 и 100 от 2011 г., бр. 7, 21, 38, 40, 44, 58, 81, 89, 94 и 99 от 2012 г., бр. 15, 20, 70, 98, 104, 106, 109 и 111 от 2013 г., бр. 1, 18, 27, 35, 53 и 107 от 2014 г., бр. 12, 14, 22, 54, 61, 79, 95, 98 и 102 от 2015 г., бр. 62, 95, 98 и 105 от 2016 г., бр. 62, 92, 99 и 103 от 2017 г., бр. 7 и 15 от 2018 г.; попр., бр. 16 от 2018 г.; изм., бр. 17, 30, 46, 53, 64, 77, 88, 98, 102 и 105 от 2018 г., бр. 12, 35, 83, 94 и 99 от 2019 г., бр. 26, 28, 51, 64, 69, 103 и 109 от 2020 г. и бр. 12, 19 и 21 от 2021 г.) се правят следните изменения и допълнения:\n1. В чл. 70 ал. 1 се изменя така:\n„(1) Размерът на пенсията за осигурителен стаж и възраст се определя, като доходът, от който се изчислява пенсията, се умножи с процент:\n1. 1,35 за всяка година осигурителен стаж без превръщане и съответната пропорционална част от този процент за месеците осигурителен стаж без превръщане;\n2. 1,2 за всяка година осигурителен стаж и съответната пропорционална част от този процент за месеците осигурителен стаж – за осигурителния стаж, представляващ разлика между общия осигурителен стаж, зачетен на лицето, и стажа по т. 1.“\n2. В чл. 75, ал. 1 числото „1,2“ се заменя с „1,35“.\n3. В чл. 79, ал. 1:\nа) в т. 1 числото „0,4494“ се заменя с „0,5056“;\nб) в т. 2 числото „0,3932“ се заменя с „0,4424“;\nв) в т. 3 числото „0,3371“ се заменя с „0,3792“.\n4. В преходните и заключителните разпоредби се създава § 7е:\n„§ 7е. (1) Отпуснатите с начална дата до 24 декември 2021 г. включително пенсии се преизчисляват от 25 декември 2021 г. с процент 1,35 на сто за всяка година осигурителен стаж без превръщане и съответната пропорционална част от този процент за месеците осигурителен стаж без превръщане. Пенсиите за трудова злополука и професионална болест, отпуснати с начална дата до 24 декември 2021 г. включително, се преизчисляват от 25 декември 2021 г. със съответния коефициент по чл. 79, ал. 1.\n(2) Преизчисляването по ал. 1 се извършва, без да се променя доходът, от който е изчислена пенсията, след което тя се осъвременява, преизчислява и индексира съобразно нормативната уредба, действаща от датата на отпускането є до 24 декември 2021 г. включително.\n(3) Преизчисляването на пенсиите по ал. 1 се извършва, ако това е по-благоприятно за лицето.“\n§ 14. Законът влиза в сила от 1 септември 2021 г., с изключение на § 9, § 11, т. 2 и § 13, които влизат в сила от 25 декември 2021 г.\nЗаконът е приет от 46-ото Народно събрание на 9 септември 2021 г. и е подпечатан с официалния печат на Народното събрание.\nПредседател на Народното събрание: Ива Митева\n5481"
    }
  ],
  "definitions": []
}