{
  "id": "act-164106",
  "type": "statute",
  "title": "Закон за ратифициране на Второто изменение на Меморандума за разбирателство между Министерството на отбраната на Република България, Министерството на отбраната на Република Естония, Министерството на отбраната на Република Финландия, правителството на Република Унгария, Министерството на националната отбрана на Република Литва, министъра на отбраната на Кралство Нидерландия, Министерството на отбраната на Кралство Норвегия, министъра на националната отбрана на Република Полша, правителството на Румъния, Министерството на отбраната на Република Словения, правителството на Кралство Швеция и Департамента по отбрана на Съединените американски щати относно способности за стратегически въздушни превози",
  "short_name": "47-202-02-10",
  "status": "in_force",
  "issued_date": "2022-04-06",
  "in_force_date": "2022-05-18",
  "url": "https://www.parliament.bg/bg/laws/ID/164106",
  "description": "Official promulgated act published by the National Assembly of the Republic of Bulgaria (act ID 164106).",
  "provisions": [
    {
      "provision_ref": "body",
      "section": "body",
      "title": "Основен текст",
      "content": "УКАЗ № 136\nНа основание чл. 98, т. 4 от Конституцията на Република България\nПОСТАНОВЯВАМ:\nДа се обнародва в „Държавен вестник“ Законът за ратифициране на Второто изменение на Меморандума за разбирателство между Министерството на отбраната на Република България, Министерството на отбраната на Република Естония, Министерството на отбраната на Република Финландия, правителството на Република Унгария, Министерството на националната отбрана на Република Литва, министъра на отбраната на Кралство Нидерландия, Министерството на отбраната на Кралство Норвегия, министъра на националната отбрана на Република Полша, правителството на Румъния, Министерството на отбраната на Република Словения, правителството на Кралство Швеция и Департамента по отбрана на Съединените американски щати относно способности за стратегически въздушни превози, приет от 47-ото Народно събрание на 18 май 2022 г.\nИздаден в София на 25 май 2022 г.\nПрезидент на Републиката: Румен Радев\nПодпечатан с държавния печат.\nМинистър на правосъдието: Надежда Йорданова\nЗАКОН\nза ратифициране на Второто изменение на Меморандума за разбирателство между Министерството на отбраната на Република България, Министерството на отбраната на Република Естония, Министерството на отбраната на Република Финландия, правителството на Република Унгария, Министерството на националната отбрана на Република Литва, министъра на отбраната на Кралство Нидерландия, Министерството на отбраната на Кралство Норвегия, министъра на националната отбрана на Република Полша, правителството на Румъния, Министерството на отбраната на Република Словения, правителството на Кралство Швеция и Департамента по отбрана на Съединените американски щати относно способности за стратегически въздушни превози\nЧлен единствен. Ратифицира Второто изменение на Меморандума за разбирателство между Министерството на отбраната на Република България, Министерството на отбраната на Република Естония, Министерството на отбраната на Република Финландия, правителството на Република Унгария, Министерството на националната отбрана на Република Литва, министъра на отбраната на Кралство Нидерландия, Министерството на отбраната на Кралство Норвегия, министъра на националната отбрана на Република Полша, правителството на Румъния, Министерството на отбраната на Република Словения, правителството на Кралство Швеция и Департамента по отбрана на Съединените американски щати относно способности за стратегически въздушни превози, подписано от българска страна на 1 септември 2020 г. в София.\nЗаключителна разпоредба\nПараграф единствен. Законът влиза в сила от деня на обнародването му в „Държавен вестник“.\nЗаконът е приет от 47-ото Народно събрание на 18 май 2022 г. и е подпечатан с официалния печат на Народното събрание.\nПредседател на Народното събрание: Никола Минчев\n3088"
    }
  ],
  "definitions": []
}